pinball/__init__.py
pinball/_version.py
pinball/playfield.py
pinball/utils.py
pinball/parts/PinballPart.py
pinball/parts/__init__.py
pinball/parts/ballhole.py
pinball/parts/flipper.py
pinball/parts/inserts.py
pinball/parts/laneguide.py
pinball/parts/launcher.py
pinball/parts/popbumper.py
pinball/parts/post.py
pinball/parts/rollover.py
pinball/parts/rubber.py
pinball/parts/slingshot.py
pinball/parts/standuptarget.py
pinball/parts/stud.py
solidpinball-0.1.1.dist-info/METADATA
solidpinball-0.1.1.dist-info/WHEEL
solidpinball-0.1.1.dist-info/top_level.txt
solidpinball-0.1.1.dist-info/RECORD
